LICENSE-MIT
MANIFEST.in
README.md
setup.py
django_sekizai_processors.egg-info/PKG-INFO
django_sekizai_processors.egg-info/SOURCES.txt
django_sekizai_processors.egg-info/dependency_links.txt
django_sekizai_processors.egg-info/not-zip-safe
django_sekizai_processors.egg-info/requires.txt
django_sekizai_processors.egg-info/top_level.txt
sekizai_processors/__init__.py
sekizai_processors/sass_preprocessor.py
sekizai_processors/management/__init__.py
sekizai_processors/management/commands/__init__.py
sekizai_processors/management/commands/compilescss.py
sekizai_processors/templatetags/__init__.py
sekizai_processors/templatetags/sekizai_processors.py