Metadata-Version: 1.1
Name: django-sekizai-processors
Version: 0.1.1
Summary: Processors to (also offline) compile SASS/SCSS files when used with django-sekizai
Home-page: https://github.com/jrief/django-sekizai-processors
Author: Jacob Rief
Author-email: jacob.rief@gmail.com
License: LICENSE-MIT
Platform: OS Independent
Classifier: Development Status :: 4 - Beta
Classifier: Environment :: Web Environment
Classifier: Framework :: Django
Classifier: Intended Audience :: Developers
Classifier: License :: OSI Approved :: MIT License
Classifier: Operating System :: OS Independent
Classifier: Programming Language :: Python
Classifier: Topic :: Internet :: WWW/HTTP :: Dynamic Content
Classifier: Programming Language :: Python :: 2.7
